latch_cloud_clients/__init__.py
latch_cloud_clients/aws/__init__.py
latch_cloud_clients/aws/storage_client.py
latch_cloud_clients/gcp/__init__.py
latch_cloud_clients/gcp/client_pool.py
latch_cloud_clients/gcp/storage.py
latch_cloud_clients/gcp/storage_client.py
latch_cloud_clients/get_storage_client.py
latch_cloud_clients/py.typed
latch_cloud_clients/utils.py
latch_cloud_clients-0.2.4.dist-info/LICENSE
latch_cloud_clients-0.2.4.dist-info/METADATA
latch_cloud_clients-0.2.4.dist-info/WHEEL
latch_cloud_clients-0.2.4.dist-info/RECORD
